komidl/__init__.py
komidl/__main__.py
komidl/constants.py
komidl/exceptions.py
komidl/komidl.py
komidl/scraper.py
komidl/status.py
komidl/extractors/__init__.py
komidl/extractors/ehentai.py
komidl/extractors/extractor.py
komidl/extractors/extractors.py
komidl/extractors/hentai2read.py
komidl/extractors/imgur.py
komidl/extractors/mangadex.py
komidl/extractors/mangahub.py
komidl/extractors/mangasushi.py
komidl/extractors/nhentai.py
komidl/extractors/tsumino.py
tests/__init__.py
tests/test_extractors.py
tests/test_scraper.py
tests/test_status.py
KomiDL-0.5.5.dist-info/LICENSE
KomiDL-0.5.5.dist-info/METADATA
KomiDL-0.5.5.dist-info/WHEEL
KomiDL-0.5.5.dist-info/entry_points.txt
KomiDL-0.5.5.dist-info/top_level.txt
KomiDL-0.5.5.dist-info/RECORD
