Metadata-Version: 2.1
Name: KomiDL
Version: 0.5.5
Summary: A downloader for image galleries and pages
Home-page: https://gitlab.com/dnsheng/komidl
Author: Dan Sheng
Author-email: dnsheng@gmail.com
License: LICENSE
Platform: UNKNOWN
Classifier: Environment :: Console
Classifier: Development Status :: 3 - Alpha
Classifier: Intended Audience :: End Users/Desktop
Classifier: License :: OSI Approved :: GNU General Public License v3 (GPLv3)
Classifier: Operating System :: MacOS
Classifier: Operating System :: Microsoft
Classifier: Operating System :: POSIX
Classifier: Programming Language :: Python :: 3.6
Classifier: Topic :: Multimedia :: Graphics
Requires-Python: >3.6.0
Requires-Dist: requests
Requires-Dist: beautifulsoup4
Requires-Dist: Pillow
